Workbook

Sheet Executive Dashboard
A1: EXECUTIVE BUSINESS BUDGET DASHBOARD | U1: KEY FINANCIAL METRICS
U2: Profit Margin | Z2: ='Annual Summary'!C11 -> 0.16666667
U3: Expense Ratio | Z3: ='Annual Summary'!C12 -> 0.83333333
U4: Total Savings | Z4: ='Annual Summary'!C10 -> 10000
A5: Comprehensive Bi-Monthly & Annual Financial Performance Tracker | U5: 📊 INCOME VS EXPENSES | XEZ5: Period | XFA5: Expenses | XFB5: Income | XFC5: Current Period
XEZ6: Jan-Feb | XFA6: ='Jan-Feb'!C14 -> 50000 | XFB6: ='Jan-Feb'!C16 -> 60000 | XFC6: =IF(XEZ6=$O$14,XFA6,NA()) -> 50000
XEZ7: Mar-Apr | XFA7: ='Mar-Apr'!C13 -> 0 | XFB7: ='Mar-Apr'!C15 -> 0 | XFC7: =IF(XEZ7=$O$14,XFA7,NA()) -> #N/A
B8: 💰 Starting Balance | F8: 📊 Ending Balance | J8: 💵 Total Income | N8: 💳 Total Expenses | XEZ8: May-Jun | XFA8: ='May-Jun'!C13 -> 0 | XFB8: ='May-Jun'!C15 -> 0 | XFC8: =IF(XEZ8=$O$14,XFA8,NA()) -> #N/A
XEZ9: Jul-Aug | XFA9: ='Jul-Aug'!C13 -> 0 | XFB9: ='Jul-Aug'!C15 -> 0 | XFC9: =IF(XEZ9=$O$14,XFA9,NA()) -> #N/A
B10: ='Annual Summary'!C5 -> 1000000 | F10: ='Annual Summary'!C6 -> 1010000 | J10: ='Annual Summary'!C9 -> 60000 | N10: ='Annual Summary'!C8 -> 50000 | XEZ10: Sep-Oct | XFA10: ='Sep-Oct'!C13 -> 0 | XFB10: ='Sep-Oct'!C15 -> 0 | XFC10: =IF(XEZ10=$O$14,XFA10,NA()) -> #N/A
XEZ11: Nov-Dec | XFA11: ='Nov-Dec'!C13 -> 0 | XFB11: ='Nov-Dec'!C15 -> 0 | XFC11: =IF(XEZ11=$O$14,XFA11,NA()) -> #N/A
L14: Current Period: | O14: Jan-Feb
D15: 📈 EXPENSE TRENDS

Sheet Annual Summary
A1: ANNUAL FINANCIAL SUMMARY REPORT
A2: Consolidated Annual Budget Performance
A4: Financial Metric | C4: Amount (₦)
A5: Starting Balance | C5: 1000000
A6: Ending Balance | C6: =C5+C10 -> 1010000
A7: Total Planned Expenses | C7: =SUM('Jan-Feb'!B14,'Mar-Apr'!B13,'May-Jun'!B13,'Jul-Aug'!B13,'Sep-Oct'!B13,'Nov-Dec'!B13) -> 40000
A8: Total Actual Expenses | C8: =SUM('Jan-Feb'!C14,'Mar-Apr'!C13,'May-Jun'!C13,'Jul-Aug'!C13,'Sep-Oct'!C13,'Nov-Dec'!C13) -> 50000
A9: Total Actual Income | C9: =SUM('Jan-Feb'!C16,'Mar-Apr'!C15,'May-Jun'!C15,'Jul-Aug'!C15,'Sep-Oct'!C15,'Nov-Dec'!C15) -> 60000
A10: Total Savings | C10: =C9-C8 -> 10000
A11: Profit Margin (%) | C11: =IF(C9=0,0,(C9-C8)/C9) -> 0.16666667
A12: Expense Ratio (%) | C12: =IF(C9=0,0,C8/C9) -> 0.83333333

Sheet Jan-Feb
A1: HAJJ BATUUL NIGERIA LIMITED
A2: JAN-FEB BUDGET PERFORMANCE
A4: Start Balance: | B4: End Balance:
A5: ='Annual Summary'!C5 -> 1000000 | B5: =A5+B18 -> 1010000
A7: 💳 EXPENSE BREAKDOWN
A8: Category | B8: Planned (₦) | C8: Actual (₦) | D8: Variance (₦) | E8: Variance (%)
A9: Commodities Fee | B9: 40000 | C9: 35000 | D9: =B9-C9 -> 5000 | E9: =IF(B9=0,0,D9/B9) -> 0.125
A10: Shipping Fee | B10: 0 | C10: 5000 | D10: =B10-C10 -> -5000 | E10: =IF(B10=0,0,D10/B10) -> 0
A11: Local Logistics Fee | B11: 0 | C11: 10000 | D11: =B11-C11 -> -10000 | E11: =IF(B11=0,0,D11/B11) -> 0
A12: Sponsored Meta Ads | B12: 0 | C12: 0 | D12: =B12-C12 -> 0 | E12: =IF(B12=0,0,D12/B12) -> 0
A13: Delivery Fee | B13: 0 | C13: 0 | D13: =B13-C13 -> 0 | E13: =IF(B13=0,0,D13/B13) -> 0
A14: TOTAL EXPENSES | B14: =SUM(B9:B13) -> 40000 | C14: =SUM(C9:C13) -> 50000 | D14: =B14-C14 -> -10000 | E14: =IF(B14=0,0,D14/B14) -> -0.25
A15: 💵 INCOME SUMMARY
A16: Actual Income | C16: 60000
A18: 💰 TOTAL SAVINGS | B18: =C16-C14 -> 10000

Sheet Mar-Apr
A1: MAR-APR BUDGET PERFORMANCE
A3: Start Balance: | B3: End Balance:
A4: ='Jan-Feb'!B5 -> 1010000 | B4: =A4+B17 -> 1010000
A6: 💳 EXPENSE BREAKDOWN
A7: Category | B7: Planned (₦) | C7: Actual (₦) | D7: Variance (₦) | E7: Variance (%)
A8: Commodities Fee | B8: 0 | C8: 0 | D8: =B8-C8 -> 0 | E8: =IF(B8=0,0,D8/B8) -> 0
A9: Shipping Fee | B9: 0 | C9: 0 | D9: =B9-C9 -> 0 | E9: =IF(B9=0,0,D9/B9) -> 0
A10: Local Logistics Fee | B10: 0 | C10: 0 | D10: =B10-C10 -> 0 | E10: =IF(B10=0,0,D10/B10) -> 0
A11: Sponsored Meta Ads | B11: 0 | C11: 0 | D11: =B11-C11 -> 0 | E11: =IF(B11=0,0,D11/B11) -> 0
A12: Delivery Fee | B12: 0 | C12: 0 | D12: =B12-C12 -> 0 | E12: =IF(B12=0,0,D12/B12) -> 0
A13: TOTAL EXPENSES | B13: =SUM(B8:B12) -> 0 | C13: =SUM(C8:C12) -> 0 | D13: =B13-C13 -> 0 | E13: =IF(B13=0,0,D13/B13) -> 0
A14: 💵 INCOME SUMMARY
A15: Actual Income | C15: 0
A17: 💰 TOTAL SAVINGS | B17: =C15-C13 -> 0

Sheet May-Jun
A1: MAY-JUN BUDGET PERFORMANCE
A3: Start Balance: | B3: End Balance:
A4: ='Mar-Apr'!B4 -> 1010000 | B4: =A4+B17 -> 1010000
A6: 💳 EXPENSE BREAKDOWN
A7: Category | B7: Planned (₦) | C7: Actual (₦) | D7: Variance (₦) | E7: Variance (%)
A8: Commodities Fee | B8: 0 | C8: 0 | D8: =B8-C8 -> 0 | E8: =IF(B8=0,0,D8/B8) -> 0
A9: Shipping Fee | B9: 0 | C9: 0 | D9: =B9-C9 -> 0 | E9: =IF(B9=0,0,D9/B9) -> 0
A10: Local Logistics Fee | B10: 0 | C10: 0 | D10: =B10-C10 -> 0 | E10: =IF(B10=0,0,D10/B10) -> 0
A11: Sponsored Meta Ads | B11: 0 | C11: 0 | D11: =B11-C11 -> 0 | E11: =IF(B11=0,0,D11/B11) -> 0
A12: Delivery Fee | B12: 0 | C12: 0 | D12: =B12-C12 -> 0 | E12: =IF(B12=0,0,D12/B12) -> 0
A13: TOTAL EXPENSES | B13: =SUM(B8:B12) -> 0 | C13: =SUM(C8:C12) -> 0 | D13: =B13-C13 -> 0 | E13: =IF(B13=0,0,D13/B13) -> 0
A14: 💵 INCOME SUMMARY
A15: Actual Income | C15: 0
A17: 💰 TOTAL SAVINGS | B17: =C15-C13 -> 0

Sheet Jul-Aug
A1: JUL-AUG BUDGET PERFORMANCE
A3: Start Balance: | B3: End Balance:
A4: ='May-Jun'!B4 -> 1010000 | B4: =A4+B17 -> 1010000
A6: 💳 EXPENSE BREAKDOWN
A7: Category | B7: Planned (₦) | C7: Actual (₦) | D7: Variance (₦) | E7: Variance (%)
A8: Commodities Fee | B8: 0 | C8: 0 | D8: =B8-C8 -> 0 | E8: =IF(B8=0,0,D8/B8) -> 0
A9: Shipping Fee | B9: 0 | C9: 0 | D9: =B9-C9 -> 0 | E9: =IF(B9=0,0,D9/B9) -> 0
A10: Local Logistics Fee | B10: 0 | C10: 0 | D10: =B10-C10 -> 0 | E10: =IF(B10=0,0,D10/B10) -> 0
A11: Sponsored Meta Ads | B11: 0 | C11: 0 | D11: =B11-C11 -> 0 | E11: =IF(B11=0,0,D11/B11) -> 0
A12: Delivery Fee | B12: 0 | C12: 0 | D12: =B12-C12 -> 0 | E12: =IF(B12=0,0,D12/B12) -> 0
A13: TOTAL EXPENSES | B13: =SUM(B8:B12) -> 0 | C13: =SUM(C8:C12) -> 0 | D13: =B13-C13 -> 0 | E13: =IF(B13=0,0,D13/B13) -> 0
A14: 💵 INCOME SUMMARY
A15: Actual Income | C15: 0
A17: 💰 TOTAL SAVINGS | B17: =C15-C13 -> 0

Sheet Sep-Oct
A1: SEP-OCT BUDGET PERFORMANCE
A3: Start Balance: | B3: End Balance:
A4: ='Jul-Aug'!B4 -> 1010000 | B4: =A4+B17 -> 1010000
A6: 💳 EXPENSE BREAKDOWN
A7: Category | B7: Planned (₦) | C7: Actual (₦) | D7: Variance (₦) | E7: Variance (%)
A8: Commodities Fee | B8: 0 | C8: 0 | D8: =B8-C8 -> 0 | E8: =IF(B8=0,0,D8/B8) -> 0
A9: Shipping Fee | B9: 0 | C9: 0 | D9: =B9-C9 -> 0 | E9: =IF(B9=0,0,D9/B9) -> 0
A10: Local Logistics Fee | B10: 0 | C10: 0 | D10: =B10-C10 -> 0 | E10: =IF(B10=0,0,D10/B10) -> 0
A11: Sponsored Meta Ads | B11: 0 | C11: 0 | D11: =B11-C11 -> 0 | E11: =IF(B11=0,0,D11/B11) -> 0
A12: Delivery Fee | B12: 0 | C12: 0 | D12: =B12-C12 -> 0 | E12: =IF(B12=0,0,D12/B12) -> 0
A13: TOTAL EXPENSES | B13: =SUM(B8:B12) -> 0 | C13: =SUM(C8:C12) -> 0 | D13: =B13-C13 -> 0 | E13: =IF(B13=0,0,D13/B13) -> 0
A14: 💵 INCOME SUMMARY
A15: Actual Income | C15: 0
A17: 💰 TOTAL SAVINGS | B17: =C15-C13 -> 0

Sheet Nov-Dec
A1: NOV-DEC BUDGET PERFORMANCE
A3: Start Balance: | B3: End Balance:
A4: ='Sep-Oct'!B4 -> 1010000 | B4: =A4+B17 -> 1010000
A6: 💳 EXPENSE BREAKDOWN
A7: Category | B7: Planned (₦) | C7: Actual (₦) | D7: Variance (₦) | E7: Variance (%)
A8: Commodities Fee | B8: 0 | C8: 0 | D8: =B8-C8 -> 0 | E8: =IF(B8=0,0,D8/B8) -> 0
A9: Shipping Fee | B9: 0 | C9: 0 | D9: =B9-C9 -> 0 | E9: =IF(B9=0,0,D9/B9) -> 0
A10: Local Logistics Fee | B10: 0 | C10: 0 | D10: =B10-C10 -> 0 | E10: =IF(B10=0,0,D10/B10) -> 0
A11: Sponsored Meta Ads | B11: 0 | C11: 0 | D11: =B11-C11 -> 0 | E11: =IF(B11=0,0,D11/B11) -> 0
A12: Delivery Fee | B12: 0 | C12: 0 | D12: =B12-C12 -> 0 | E12: =IF(B12=0,0,D12/B12) -> 0
A13: TOTAL EXPENSES | B13: =SUM(B8:B12) -> 0 | C13: =SUM(C8:C12) -> 0 | D13: =B13-C13 -> 0 | E13: =IF(B13=0,0,D13/B13) -> 0
A14: 💵 INCOME SUMMARY
A15: Actual Income | C15: 0
A17: 💰 TOTAL SAVINGS | B17: =C15-C13 -> 0
