Workbook

Sheet Investor Dashboard
A1: INVESTOR MANAGEMENT SYSTEM | Z1: 📊 CAPITAL DISTRIBUTION BY INVESTOR
A6: Comprehensive Investor Portfolio & ROI Tracking Dashboard
B8: 📅 Select Month for ROI/Dividend Tracking: | F8: November
B10: 👥 Total Investors | H10: 💰 Total Capital | N10: 📈 Monthly ROI Total | T10: ✅ Active Investors
B12: =COUNTA('Investor Records'!B5:B999) -> 3 | H12: =SUMIFS('Payment Tracker'!D:D,'Payment Tracker'!C:C,"Capital",'Payment Tracker'!H:H,"Completed",'Investor Records'!J:J,"Active") -> 0 | N12: =SUMIFS('Payment Tracker'!$D:$D,'Payment Tracker'!$C:$C,"Dividend",'Payment Tracker'!$H:$H,"Completed",'Payment Tracker'!$E:$E,">="&DATE(YEAR(TODAY()),MATCH($F$8,{"January","February","March","April","May","June","July","August","September","October","November","December"},0),1),'Payment Tracker'!$E:$E,"<"&DATE(YEAR(TODAY()),MATCH($F$8,{"January","February","March","April","May","June","July","August","September","October","November","December"},0)+1,1)) -> 50000 | T12: =COUNTIF('Investor Records'!J5:J999,"Active") -> 3
Z14: 💹 ROI PERFORMANCE OVERVIEW
B16: 💳 Capital Paid | H16: ⏳ Capital Pending | N16: ✔️ Dividend Paid | T16: ⏰ Dividend Pending
B18: =SUMPRODUCT(('Payment Tracker'!$C$5:$C$1000="Capital")*('Payment Tracker'!$H$5:$H$1000="Completed")*('Payment Tracker'!$A$5:$A$1000<>"")*COUNTIFS('Investor Records'!$A$5:$A$999,'Payment Tracker'!$A$5:$A$1000,'Investor Records'!$J$5:$J$999,"Active")) -> 0 | H18: =SUMPRODUCT(('Payment Tracker'!$C$5:$C$1000="Capital")*('Payment Tracker'!$H$5:$H$1000="Pending")*('Payment Tracker'!$A$5:$A$1000<>"")*COUNTIFS('Investor Records'!$A$5:$A$999,'Payment Tracker'!$A$5:$A$1000,'Investor Records'!$J$5:$J$999,"Active")) -> 0 | N18: =SUMPRODUCT(('Payment Tracker'!$C$5:$C$1000="Dividend")*('Payment Tracker'!$H$5:$H$1000="Completed")*(MONTH('Payment Tracker'!$E$5:$E$1000)=MATCH($F$8,{"January","February","March","April","May","June","July","August","September","October","November","December"},0))*('Payment Tracker'!$A$5:$A$1000<>"")*COUNTIFS('Investor Records'!$A$5:$A$999,'Payment Tracker'!$A$5:$A$1000,'Investor Records'!$J$5:$J$999,"Active")) -> 1 | T18: =SUMPRODUCT(('Payment Tracker'!$C$5:$C$1000="Dividend")*('Payment Tracker'!$H$5:$H$1000="Pending")*(MONTH('Payment Tracker'!$E$5:$E$1000)=MATCH($F$8,{"January","February","March","April","May","June","July","August","September","October","November","December"},0))*('Payment Tracker'!$A$5:$A$1000<>"")*COUNTIFS('Investor Records'!$A$5:$A$999,'Payment Tracker'!$A$5:$A$1000,'Investor Records'!$J$5:$J$999,"Active")) -> 0
B22: 💸 Total Refunds
B24: =SUMIFS('Payment Tracker'!D:D,'Payment Tracker'!C:C,"Refund",'Payment Tracker'!H:H,"Completed") -> 1000000

Sheet Investor Records
A1: COMPREHENSIVE INVESTOR RECORDS DATABASE
A2: Complete Investor Information & Financial Tracking
A4: Investor Tally # | B4: Investor Name | C4: Investor Address | D4: Investment Capital (₦) | E4: Monthly ROI (₦) | F4: Date of Investment | G4: Bank Name | H4: Account Name | I4: Account Number | J4: Active/Inactive
A5: 1 | B5: Sample 1 | C5: 123 Investment Street, Lagos | D5: 500000 | E5: 60000 | J5: Active
A6: 2 | B6: Sample 2 | C6: 123 Investment Street, Lagos | D6: 500000 | E6: 50000 | J6: Active
A7: 3 | B7: Sample 3 | C7: 123 Investment Street, Lagos | D7: 1000000 | E7: 100000 | J7: Active

Sheet Payment Tracker
A1: INVESTOR PAYMENT TRACKING SYSTEM
A2: Track Capital & Dividend Payment History
A4: Tally # | B4: Investor Name | C4: Payment Type | D4: Amount (₦) | E4: Payment Date | F4: Payment Method | G4: Reference # | H4: Status
A5: 1 | B5: =IF($A5=InvestorTable[[#This Row],[Investor Tally '#]],InvestorTable[[#This Row],[Investor Name]], NA()) -> Sample 1 | C5: Dividend | D5: {=_xlfn.IFS(AND(InvestorTable[[#This Row],[Investor Tally '#]] = 'Payment Tracker'!$A5, 'Payment Tracker'!$C5="Dividend") = TRUE, InvestorTable[[#This Row],[Monthly ROI (₦)]], AND(InvestorTable[[#This Row],[Investor Tally '#]] = 'Payment Tracker'!$A5, 'Payment Tracker'!$C5="Capital") = TRUE, InvestorTable[[#This Row],[Investment Capital (₦)]], AND(InvestorTable[[#This Row],[Investor Tally '#]] = 'Payment Tracker'!$A5, 'Payment Tracker'!$C5="Refund") = TRUE, InvestorTable[[#This Row],[Investment Capital (₦)]] )} -> 60000 | E5: 46361 | F5: Bank Transfer | G5: hiaiwjns8892u3793 | H5: Completed
A6: 2 | B6: =IF($A6=InvestorTable[[#This Row],[Investor Tally '#]],InvestorTable[[#This Row],[Investor Name]], NA()) -> Sample 2 | C6: Dividend | D6: {=_xlfn.IFS(AND(InvestorTable[[#This Row],[Investor Tally '#]] = 'Payment Tracker'!$A6, 'Payment Tracker'!$C6="Dividend") = TRUE, InvestorTable[[#This Row],[Monthly ROI (₦)]], AND(InvestorTable[[#This Row],[Investor Tally '#]] = 'Payment Tracker'!$A6, 'Payment Tracker'!$C6="Capital") = TRUE, InvestorTable[[#This Row],[Investment Capital (₦)]], AND(InvestorTable[[#This Row],[Investor Tally '#]] = 'Payment Tracker'!$A6, 'Payment Tracker'!$C6="Refund") = TRUE, InvestorTable[[#This Row],[Investment Capital (₦)]] )} -> 50000 | E6: 46331 | F6: Bank Transfer | G6: hiaiwjns8892u3746 | H6: Completed
A7: 3 | B7: =IF($A7=InvestorTable[[#This Row],[Investor Tally '#]],InvestorTable[[#This Row],[Investor Name]], NA()) -> Sample 3 | C7: Refund | D7: {=_xlfn.IFS(AND(InvestorTable[[#This Row],[Investor Tally '#]] = 'Payment Tracker'!$A7, 'Payment Tracker'!$C7="Dividend") = TRUE, InvestorTable[[#This Row],[Monthly ROI (₦)]], AND(InvestorTable[[#This Row],[Investor Tally '#]] = 'Payment Tracker'!$A7, 'Payment Tracker'!$C7="Capital") = TRUE, InvestorTable[[#This Row],[Investment Capital (₦)]], AND(InvestorTable[[#This Row],[Investor Tally '#]] = 'Payment Tracker'!$A7, 'Payment Tracker'!$C7="Refund") = TRUE, InvestorTable[[#This Row],[Investment Capital (₦)]] )} -> 1000000 | H7: Completed
B8: =IF($A8=InvestorTable[[#This Row],[Investor Tally '#]],InvestorTable[[#This Row],[Investor Name]], NA()) -> 0 | D8: {=_xlfn.IFS(AND(InvestorTable[[#This Row],[Investor Tally '#]] = 'Payment Tracker'!$A8, 'Payment Tracker'!$C8="Dividend") = TRUE, InvestorTable[[#This Row],[Monthly ROI (₦)]], AND(InvestorTable[[#This Row],[Investor Tally '#]] = 'Payment Tracker'!$A8, 'Payment Tracker'!$C8="Capital") = TRUE, InvestorTable[[#This Row],[Investment Capital (₦)]], AND(InvestorTable[[#This Row],[Investor Tally '#]] = 'Payment Tracker'!$A8, 'Payment Tracker'!$C8="Refund") = TRUE, InvestorTable[[#This Row],[Investment Capital (₦)]] )} -> #N/A
B9: =IF($A9=InvestorTable[[#This Row],[Investor Tally '#]],InvestorTable[[#This Row],[Investor Name]], NA()) -> 0 | D9: {=_xlfn.IFS(AND(InvestorTable[[#This Row],[Investor Tally '#]] = 'Payment Tracker'!$A9, 'Payment Tracker'!$C9="Dividend") = TRUE, InvestorTable[[#This Row],[Monthly ROI (₦)]], AND(InvestorTable[[#This Row],[Investor Tally '#]] = 'Payment Tracker'!$A9, 'Payment Tracker'!$C9="Capital") = TRUE, InvestorTable[[#This Row],[Investment Capital (₦)]], AND(InvestorTable[[#This Row],[Investor Tally '#]] = 'Payment Tracker'!$A9, 'Payment Tracker'!$C9="Refund") = TRUE, InvestorTable[[#This Row],[Investment Capital (₦)]] )} -> #N/A
B10: =IF($A10=InvestorTable[[#This Row],[Investor Tally '#]],InvestorTable[[#This Row],[Investor Name]], NA()) -> 0 | D10: {=_xlfn.IFS(AND(InvestorTable[[#This Row],[Investor Tally '#]] = 'Payment Tracker'!$A10, 'Payment Tracker'!$C10="Dividend") = TRUE, InvestorTable[[#This Row],[Monthly ROI (₦)]], AND(InvestorTable[[#This Row],[Investor Tally '#]] = 'Payment Tracker'!$A10, 'Payment Tracker'!$C10="Capital") = TRUE, InvestorTable[[#This Row],[Investment Capital (₦)]], AND(InvestorTable[[#This Row],[Investor Tally '#]] = 'Payment Tracker'!$A10, 'Payment Tracker'!$C10="Refund") = TRUE, InvestorTable[[#This Row],[Investment Capital (₦)]] )} -> #N/A
B11: =IF($A11=InvestorTable[[#This Row],[Investor Tally '#]],InvestorTable[[#This Row],[Investor Name]], NA()) -> 0 | D11: {=_xlfn.IFS(AND(InvestorTable[[#This Row],[Investor Tally '#]] = 'Payment Tracker'!$A11, 'Payment Tracker'!$C11="Dividend") = TRUE, InvestorTable[[#This Row],[Monthly ROI (₦)]], AND(InvestorTable[[#This Row],[Investor Tally '#]] = 'Payment Tracker'!$A11, 'Payment Tracker'!$C11="Capital") = TRUE, InvestorTable[[#This Row],[Investment Capital (₦)]], AND(InvestorTable[[#This Row],[Investor Tally '#]] = 'Payment Tracker'!$A11, 'Payment Tracker'!$C11="Refund") = TRUE, InvestorTable[[#This Row],[Investment Capital (₦)]] )} -> #N/A
B12: =IF($A12=InvestorTable[[#This Row],[Investor Tally '#]],InvestorTable[[#This Row],[Investor Name]], NA()) -> 0 | D12: {=_xlfn.IFS(AND(InvestorTable[[#This Row],[Investor Tally '#]] = 'Payment Tracker'!$A12, 'Payment Tracker'!$C12="Dividend") = TRUE, InvestorTable[[#This Row],[Monthly ROI (₦)]], AND(InvestorTable[[#This Row],[Investor Tally '#]] = 'Payment Tracker'!$A12, 'Payment Tracker'!$C12="Capital") = TRUE, InvestorTable[[#This Row],[Investment Capital (₦)]], AND(InvestorTable[[#This Row],[Investor Tally '#]] = 'Payment Tracker'!$A12, 'Payment Tracker'!$C12="Refund") = TRUE, InvestorTable[[#This Row],[Investment Capital (₦)]] )} -> #N/A
B13: =IF($A13=InvestorTable[[#This Row],[Investor Tally '#]],InvestorTable[[#This Row],[Investor Name]], NA()) -> 0 | D13: {=_xlfn.IFS(AND(InvestorTable[[#This Row],[Investor Tally '#]] = 'Payment Tracker'!$A13, 'Payment Tracker'!$C13="Dividend") = TRUE, InvestorTable[[#This Row],[Monthly ROI (₦)]], AND(InvestorTable[[#This Row],[Investor Tally '#]] = 'Payment Tracker'!$A13, 'Payment Tracker'!$C13="Capital") = TRUE, InvestorTable[[#This Row],[Investment Capital (₦)]], AND(InvestorTable[[#This Row],[Investor Tally '#]] = 'Payment Tracker'!$A13, 'Payment Tracker'!$C13="Refund") = TRUE, InvestorTable[[#This Row],[Investment Capital (₦)]] )} -> #N/A
B14: =IF($A14=InvestorTable[[#This Row],[Investor Tally '#]],InvestorTable[[#This Row],[Investor Name]], NA()) -> 0 | D14: {=_xlfn.IFS(AND(InvestorTable[[#This Row],[Investor Tally '#]] = 'Payment Tracker'!$A14, 'Payment Tracker'!$C14="Dividend") = TRUE, InvestorTable[[#This Row],[Monthly ROI (₦)]], AND(InvestorTable[[#This Row],[Investor Tally '#]] = 'Payment Tracker'!$A14, 'Payment Tracker'!$C14="Capital") = TRUE, InvestorTable[[#This Row],[Investment Capital (₦)]], AND(InvestorTable[[#This Row],[Investor Tally '#]] = 'Payment Tracker'!$A14, 'Payment Tracker'!$C14="Refund") = TRUE, InvestorTable[[#This Row],[Investment Capital (₦)]] )} -> #N/A
B15: =IF($A15=InvestorTable[[#This Row],[Investor Tally '#]],InvestorTable[[#This Row],[Investor Name]], NA()) -> 0 | D15: {=_xlfn.IFS(AND(InvestorTable[[#This Row],[Investor Tally '#]] = 'Payment Tracker'!$A15, 'Payment Tracker'!$C15="Dividend") = TRUE, InvestorTable[[#This Row],[Monthly ROI (₦)]], AND(InvestorTable[[#This Row],[Investor Tally '#]] = 'Payment Tracker'!$A15, 'Payment Tracker'!$C15="Capital") = TRUE, InvestorTable[[#This Row],[Investment Capital (₦)]], AND(InvestorTable[[#This Row],[Investor Tally '#]] = 'Payment Tracker'!$A15, 'Payment Tracker'!$C15="Refund") = TRUE, InvestorTable[[#This Row],[Investment Capital (₦)]] )} -> #N/A
B16: =IF($A16=InvestorTable[[#This Row],[Investor Tally '#]],InvestorTable[[#This Row],[Investor Name]], NA()) -> 0 | D16: {=_xlfn.IFS(AND(InvestorTable[[#This Row],[Investor Tally '#]] = 'Payment Tracker'!$A16, 'Payment Tracker'!$C16="Dividend") = TRUE, InvestorTable[[#This Row],[Monthly ROI (₦)]], AND(InvestorTable[[#This Row],[Investor Tally '#]] = 'Payment Tracker'!$A16, 'Payment Tracker'!$C16="Capital") = TRUE, InvestorTable[[#This Row],[Investment Capital (₦)]], AND(InvestorTable[[#This Row],[Investor Tally '#]] = 'Payment Tracker'!$A16, 'Payment Tracker'!$C16="Refund") = TRUE, InvestorTable[[#This Row],[Investment Capital (₦)]] )} -> #N/A
B17: =IF($A17=InvestorTable[[#This Row],[Investor Tally '#]],InvestorTable[[#This Row],[Investor Name]], NA()) -> 0 | D17: {=_xlfn.IFS(AND(InvestorTable[[#This Row],[Investor Tally '#]] = 'Payment Tracker'!$A17, 'Payment Tracker'!$C17="Dividend") = TRUE, InvestorTable[[#This Row],[Monthly ROI (₦)]], AND(InvestorTable[[#This Row],[Investor Tally '#]] = 'Payment Tracker'!$A17, 'Payment Tracker'!$C17="Capital") = TRUE, InvestorTable[[#This Row],[Investment Capital (₦)]], AND(InvestorTable[[#This Row],[Investor Tally '#]] = 'Payment Tracker'!$A17, 'Payment Tracker'!$C17="Refund") = TRUE, InvestorTable[[#This Row],[Investment Capital (₦)]] )} -> #N/A
B18: =IF($A18=InvestorTable[[#This Row],[Investor Tally '#]],InvestorTable[[#This Row],[Investor Name]], NA()) -> 0 | D18: {=_xlfn.IFS(AND(InvestorTable[[#This Row],[Investor Tally '#]] = 'Payment Tracker'!$A18, 'Payment Tracker'!$C18="Dividend") = TRUE, InvestorTable[[#This Row],[Monthly ROI (₦)]], AND(InvestorTable[[#This Row],[Investor Tally '#]] = 'Payment Tracker'!$A18, 'Payment Tracker'!$C18="Capital") = TRUE, InvestorTable[[#This Row],[Investment Capital (₦)]], AND(InvestorTable[[#This Row],[Investor Tally '#]] = 'Payment Tracker'!$A18, 'Payment Tracker'!$C18="Refund") = TRUE, InvestorTable[[#This Row],[Investment Capital (₦)]] )} -> #N/A
B19: =IF($A19=InvestorTable[[#This Row],[Investor Tally '#]],InvestorTable[[#This Row],[Investor Name]], NA()) -> 0 | D19: {=_xlfn.IFS(AND(InvestorTable[[#This Row],[Investor Tally '#]] = 'Payment Tracker'!$A19, 'Payment Tracker'!$C19="Dividend") = TRUE, InvestorTable[[#This Row],[Monthly ROI (₦)]], AND(InvestorTable[[#This Row],[Investor Tally '#]] = 'Payment Tracker'!$A19, 'Payment Tracker'!$C19="Capital") = TRUE, InvestorTable[[#This Row],[Investment Capital (₦)]], AND(InvestorTable[[#This Row],[Investor Tally '#]] = 'Payment Tracker'!$A19, 'Payment Tracker'!$C19="Refund") = TRUE, InvestorTable[[#This Row],[Investment Capital (₦)]] )} -> #N/A
... B1000: =IF($A1000=InvestorTable[[#This Row],[Investor Tally '#]],InvestorTable[[#This Row],[Investor Name]], NA()) -> #VALUE! | D1000: {=_xlfn.IFS(AND(InvestorTable[[#This Row],[Investor Tally '#]] = 'Payment Tracker'!$A1000, 'Payment Tracker'!$C1000="Dividend") = TRUE, InvestorTable[[#This Row],[Monthly ROI (₦)]], AND(InvestorTable[[#This Row],[Investor Tally '#]] = 'Payment Tracker'!$A1000, 'Payment Tracker'!$C1000="Capital") = TRUE, InvestorTable[[#This Row],[Investment Capital (₦)]], AND(InvestorTable[[#This Row],[Investor Tally '#]] = 'Payment Tracker'!$A1000, 'Payment Tracker'!$C1000="Refund") = TRUE, InvestorTable[[#This Row],[Investment Capital (₦)]] )} -> #VALUE!
